{
  "id": "input-tag",
  "slug": "input-tag",
  "title": "Input Tag",
  "description": "Tag entry input for labels, recipients, and multi-value fields.",
  "llmSummary": "Input Tag: Tag entry input for labels, recipients, and multi-value fields.",
  "category": "Forms",
  "status": "stable",
  "docsStatus": "draft",
  "tags": [],
  "sourcePath": "src/components/ui/inputs-advanced.tsx",
  "sourceExport": "InputTag",
  "docsPath": "src/content/docs/components/input-tag.md",
  "dependencies": [],
  "registryDependencies": [],
  "relatedComponents": [],
  "hasMarkdownDoc": false
}
